soda/data_sources/dask_connection.py
soda/data_sources/dask_cursor.py
soda/data_sources/dask_data_source.py
soda_core_pandas_dask-3.5.6.dist-info/LICENSE
soda_core_pandas_dask-3.5.6.dist-info/METADATA
soda_core_pandas_dask-3.5.6.dist-info/WHEEL
soda_core_pandas_dask-3.5.6.dist-info/top_level.txt
soda_core_pandas_dask-3.5.6.dist-info/RECORD
