Metadata-Version: 2.1
Name: soda-core-pandas-dask
Version: 3.5.6
License-File: LICENSE
Requires-Dist: soda-core==3.5.6
Requires-Dist: dask>=2022.10.0
Requires-Dist: dask-sql<2023.10.0,>=2022.12.0
